{
    "name": "SUNNY BOY STORAGE 2.5",
    "config": {
        "id": "7",
        "values": {
            "6100_00295A00": {
                "name": "charge_percent",
            "divider": 1
            },
            "6100_00495C00": {
                "name": "voltage",
                "divider": 100
            },
            "6400_00496700": {
                "name": "overall_charge_wh",
                "divider": 1
            },
            "6100_00496900": {
                "name": "current_charging_w",
                "divider": 1
            },
            "6400_00497E00": {
                "name": "current_charging_wh",
                "divider": 1
            },
            "6400_00496800": {
                "name": "overall_discharge_wh",
                "divider": 1
            },
            "6100_00496A00": {
                "name": "current_discharge_w",
                "divider": 1
            },
            "6400_00496D00": {
                "name": "current_discharge_wh",
                "divider": 1
            },
            "6400_00496900": {
                "name": "charge_w",
                "divider": 1
            },
            "6100_40495B00": {
                "name": "temperature_deg",
                "divider": 10
            },
            "6180_08495E00": {
                "name": "state_charging",
                "divider": 1
            }
        }
    }
}